{
  "timestamp": "2026-07-03T12:05:32.492556-06:00",
  "current_date": "2026-07-03",
  "current_time": "12:05",
  "timezone": "America/Guatemala",
  "live": {
    "team1": "2D",
    "team2": "2G",
    "minute": 5,
    "minute_display": "5'",
    "score1": 0,
    "score2": 0,
    "stadium": "Dallas (Arlington)",
    "date": "2026-07-03",
    "time": "12:00 UTC-6",
    "round": "Round of 32"
  },
  "next": {
    "team1": "1J",
    "team2": "2H",
    "stadium": "Miami (Miami Gardens)",
    "date": "2026-07-03",
    "time": "16:00 UTC-6",
    "round": "Round of 32"
  },
  "has_live": true
}